retroPySim/__init__.py
retroPySim/retroPySim.py
retropysim-0.0.1.dist-info/METADATA
retropysim-0.0.1.dist-info/WHEEL
retropysim-0.0.1.dist-info/top_level.txt
retropysim-0.0.1.dist-info/RECORD
