Metadata-Version: 2.4
Name: retroPySim
Version: 0.0.1
Summary: retroPySim - a Python simulator for retroPy, a micro-python retro game engine for the RP2350 micro-controller. 
Home-page: https://www.retropy.io/
Author: ---
Author-email: retropy@respawnin.com
Classifier: Programming Language :: Python :: 3
Classifier: License :: OSI Approved :: MIT License
Classifier: Operating System :: OS Independent
Requires-Python: >=3.6
Dynamic: author
Dynamic: author-email
Dynamic: classifier
Dynamic: description
Dynamic: description-content-type
Dynamic: home-page
Dynamic: requires-python
Dynamic: summary
